{
  "html_attributions": [],
  "results": [
    {
      "formatted_address": "Quinton Rd, Coventry CV1 2WT",
      "geometry": {
        "location": {
          "lat": 52.40101319999999,
          "lng": -1.5081129
        },
        "viewport": {
          "northeast": {
            "lat": 52.40236652989272,
            "lng": -1.506725370107278
          },
          "southwest": {
            "lat": 52.39966687010728,
            "lng": -1.509425029892722
          }
        }
      },
      "icon": "https://maps.gstatic.com/mapfiles/place_api/icons/v1/png_71/geocode-71.png",
      "icon_background_color": "#7B9EB0",
      "icon_mask_base_uri": "https://maps.gstatic.com/mapfiles/place_api/icons/v2/generic_pinlet",
      "more_opening_hours": [],
      "name": "CV1 2WT",
      "place_id": "ChIJ0ctWbbFLd0gR1oUcir5Vc80",
      "reference": "ChIJ0ctWbbFLd0gR1oUcir5Vc80",
      "types": [
        "postal_code"
      ]
    }
  ],
  "status": "OK"
}